Metadata-Version: 2.1
Name: sportsreference-sio
Version: 0.4.6
Summary: A free sports API written for python
Home-page: https://github.com/roclark/sportsreference
Author: Robert Clark
Author-email: robdclark@outlook.com
License: MIT
Keywords: stats sports api sportsreference machine learning
Platform: UNKNOWN
Classifier: Programming Language :: Python :: 3.5
Classifier: Programming Language :: Python :: 3.6
Classifier: Programming Language :: Python :: 3.7
Classifier: License :: OSI Approved :: MIT License
Classifier: Operating System :: POSIX :: Linux
Requires-Python: >=3.5
Requires-Dist: pandas (>=0.24.1)
Requires-Dist: pyquery (>=1.4.0)
Requires-Dist: requests (>=2.18.4)
